{"package_name": "java.nio.file", "subclass_list": [], "class_description": "Checked exception thrown when an attempt is made to access a file that does\n not exist. ", "class_type": "class", "typealias": [], "interface_list": [""], "class_inherit_list": ["FileSystemException"], "Methods": [{"params": [{"param_name": ["file"], "param_type": "String", "param_description": " a string identifying the file or null if not known."}], "class_name": "NoSuchFileException", "is_static": false, "return_value": {"return_name": "", "return_description": [], "return_type": []}, "method_name": "init", "method_description": "Constructs an instance of this class.\n", "method_declar": ""}, {"params": [{"param_name": ["file"], "param_type": "String", "param_description": " a string identifying the file or null if not known."}, {"param_name": ["other"], "param_type": "String", "param_description": " a string identifying the other file or null if not known."}, {"param_name": ["reason"], "param_type": "String", "param_description": " a reason message with additional information or null"}], "class_name": "NoSuchFileException", "is_static": false, "return_value": {"return_name": "", "return_description": [], "return_type": []}, "method_name": "init", "method_description": "Constructs an instance of this class.\n", "method_declar": ""}], "class_name": "NoSuchFileException", "Vars": null}