{"package_name": "java.security", "subclass_list": ["DHPrivateKey", "DHPublicKey", "DSAPrivateKey", "DSAPublicKey", "ECPrivateKey", "ECPublicKey", "PBEKey", "PrivateKey", "PublicKey", "RSAMultiPrimePrivateCrtKey", "RSAPrivateCrtKey", "RSAPrivateKey", "RSAPublicKey", "SecretKey", "SecretKeySpec", "DHPrivateKey", "DHPublicKey", "DSAPrivateKey", "DSAPublicKey", "ECPrivateKey", "ECPublicKey", "PBEKey", "PrivateKey", "PublicKey", "RSAMultiPrimePrivateCrtKey", "RSAPrivateCrtKey", "RSAPrivateKey", "RSAPublicKey", "SecretKey", "SecretKeySpec"], "class_description": "The Key interface is the top-level interface for all keys. It\n defines the functionality shared by all key objects. All keys\n have three characteristics: A Key should use KeyRep as its serialized representation.\n Note that a serialized Key may contain sensitive information\n which should not be exposed in untrusted environments.  See the\n \n Security Appendix\n of the Serialization Specification for more information. ", "class_type": "interface", "typealias": [], "interface_list": ["Serializable"], "class_inherit_list": [], "Methods": [], "class_name": "Key", "Vars": null}