{"package_name": "javax.net.ssl", "subclass_list": [], "class_description": "HttpsURLConnection extends HttpURLConnection\n with support for https-specific features. See \n http://www.w3.org/pub/WWW/Protocols/ and\n  RFC 2818 \n for more details on the\n https specification. This class uses HostnameVerifier and\n SSLSocketFactory.\n There are default implementations defined for both classes.\n However, the implementations can be replaced on a per-class (static) or\n per-instance basis.  All new HttpsURLConnections instances\n will be assigned\n the \"default\" static values at instance creation, but they can be overriden\n by calling the appropriate per-instance set method(s) before\n connecting. ", "class_type": "class", "typealias": [], "interface_list": [""], "class_inherit_list": ["HttpURLConnection"], "Methods": [], "class_name": "HttpsURLConnection", "Vars": null}